isjosh18/__init__.py
isjosh18/__main__.py
isjosh18-0.12.dist-info/METADATA
isjosh18-0.12.dist-info/RECORD
isjosh18-0.12.dist-info/WHEEL
isjosh18-0.12.dist-info/entry_points.txt
isjosh18-0.12.dist-info/top_level.txt
