Metadata-Version: 2.1
Name: isjosh18
Version: 0.12
Summary: Determines if Josh is 18.
Home-page: https://github.com/numirias/python-isjosh18
Author: numirias
Author-email: numirias@users.noreply.github.com
License: MIT
Platform: UNKNOWN
Classifier: Development Status :: 4 - Beta
Classifier: License :: OSI Approved :: MIT License
Classifier: Programming Language :: Python
Classifier: Programming Language :: Python :: 2.7
Classifier: Programming Language :: Python :: 3
Classifier: Programming Language :: Python :: 3.5
Classifier: Programming Language :: Python :: 3.6
Classifier: Programming Language :: Python :: 3.7
Requires-Python: >=2.7
Requires-Dist: requests
Requires-Dist: colorama
Requires-Dist: mock
